pdudaemon/__init__.py
pdudaemon/httplistener.py
pdudaemon/listener.py
pdudaemon/pdurunner.py
pdudaemon/tcplistener.py
pdudaemon/drivers/__init__.py
pdudaemon/drivers/acme.py
pdudaemon/drivers/acmebase.py
pdudaemon/drivers/anelnetpwrctrl.py
pdudaemon/drivers/apc7900.py
pdudaemon/drivers/apc7920.py
pdudaemon/drivers/apc7921.py
pdudaemon/drivers/apc7932.py
pdudaemon/drivers/apc7952.py
pdudaemon/drivers/apc8959.py
pdudaemon/drivers/apc9210.py
pdudaemon/drivers/apc9218.py
pdudaemon/drivers/apcbase.py
pdudaemon/drivers/bcu.py
pdudaemon/drivers/cleware.py
pdudaemon/drivers/conrad197720.py
pdudaemon/drivers/cyberpower81001.py
pdudaemon/drivers/devantech.py
pdudaemon/drivers/devantechusb.py
pdudaemon/drivers/driver.py
pdudaemon/drivers/egpms.py
pdudaemon/drivers/energenieusb.py
pdudaemon/drivers/esphome.py
pdudaemon/drivers/gude1202.py
pdudaemon/drivers/hiddevice.py
pdudaemon/drivers/homeassistant.py
pdudaemon/drivers/intellinet.py
pdudaemon/drivers/ip9258.py
pdudaemon/drivers/ip9850.py
pdudaemon/drivers/ipower.py
pdudaemon/drivers/localbase.py
pdudaemon/drivers/localcmdline.py
pdudaemon/drivers/modbustcp.py
pdudaemon/drivers/netio4.py
pdudaemon/drivers/numatousb.py
pdudaemon/drivers/sainsmart.py
pdudaemon/drivers/servertechpro2.py
pdudaemon/drivers/servo.py
pdudaemon/drivers/snmp.py
pdudaemon/drivers/strategies.py
pdudaemon/drivers/synaccess.py
pdudaemon/drivers/tasmota.py
pdudaemon/drivers/test_numatousb.py
pdudaemon/drivers/tplink.py
pdudaemon/drivers/ubiquity.py
pdudaemon/drivers/vusbhid.py
pdudaemon/drivers/ykush.py
pdudaemon-1.0.0.dist-info/METADATA
pdudaemon-1.0.0.dist-info/WHEEL
pdudaemon-1.0.0.dist-info/entry_points.txt
pdudaemon-1.0.0.dist-info/top_level.txt
pdudaemon-1.0.0.dist-info/RECORD
