Metadata-Version: 2.1
Name: pdudaemon
Version: 1.0.0
Summary: Control and Queueing daemon for PDUs
Maintainer-email: Matt Hart <matt@mattface.org>
License: GPL-2+
Project-URL: Homepage, https://github.com/pdudaemon/pdudaemon.git
Classifier: Development Status :: 5 - Production/Stable
Classifier: Environment :: Console
Classifier: Intended Audience :: Developers
Classifier: License :: OSI Approved :: GNU General Public License v2 or later (GPLv2+)
Classifier: Operating System :: POSIX :: Linux
Classifier: Programming Language :: Python :: 3.4
Classifier: Programming Language :: Python :: 3.5
Classifier: Programming Language :: Python :: 3.6
Classifier: Programming Language :: Python :: 3.7
Classifier: Programming Language :: Python :: 3.8
Classifier: Programming Language :: Python :: 3.9
Classifier: Programming Language :: Python :: 3.10
Classifier: Programming Language :: Python :: 3.11
Classifier: Programming Language :: Python :: 3 :: Only
Classifier: Topic :: Communications
Classifier: Topic :: Software Development :: Testing
Classifier: Topic :: System :: Networking
Requires-Python: >=3.4
Requires-Dist: aiohttp
Requires-Dist: requests
Requires-Dist: pexpect
Requires-Dist: systemd-python
Requires-Dist: paramiko
Requires-Dist: pyserial
Requires-Dist: hidapi
Requires-Dist: pysnmp <6,>=4.4.12
Requires-Dist: pyasn1 <0.6.1
Requires-Dist: pyusb
Requires-Dist: pymodbus
Provides-Extra: test
Requires-Dist: pytest >=4.6 ; extra == 'test'
Requires-Dist: pytest-mock ; extra == 'test'
